{
  "version": "1.1.1",
  "windows": {
    "main": {
      "main": true,
      "url": "app://editor/index.html",
      "windowType": "dockable",
      "x": -8,
      "y": -8,
      "width": 1296,
      "height": 696,
      "layout": {
        "children": [
          {
            "children": [
              {
                "active": 0,
                "children": [
                  "hierarchy"
                ],
                "height": 283.66668701171875,
                "type": "panel",
                "width": 204
              },
              {
                "active": 0,
                "children": [
                  "assets"
                ],
                "height": 277.66668701171875,
                "type": "panel",
                "width": 204
              }
            ],
            "height": 564.3333740234375,
            "type": "dock-v",
            "width": 204
          },
          {
            "children": [
              {
                "children": [
                  {
                    "active": 0,
                    "children": [
                      "scene"
                    ],
                    "height": 290.65625,
                    "type": "panel",
                    "width": 260.46875
                  },
                  {
                    "active": 0,
                    "children": [
                      "node-library"
                    ],
                    "height": 290.65625,
                    "type": "panel",
                    "width": 289.53125
                  }
                ],
                "height": 290.65625,
                "type": "dock-h",
                "width": 553
              },
              {
                "active": 1,
                "children": [
                  "console",
                  "timeline",
                  "game-window"
                ],
                "height": 270.6770935058594,
                "type": "panel",
                "width": 553
              }
            ],
            "height": 564.3333740234375,
            "type": "dock-v",
            "width": 553
          },
          {
            "active": 0,
            "children": [
              "inspector",
              "cocos-services"
            ],
            "height": 564.3333740234375,
            "type": "panel",
            "width": 503
          }
        ],
        "type": "dock-h"
      },
      "panels": [
        "hierarchy",
        "assets",
        "scene",
        "node-library",
        "console",
        "timeline",
        "game-window",
        "inspector",
        "cocos-services"
      ]
    },
    "worker": {}
  },
  "panels": {
    "sprite-editor": {
      "x": -8,
      "y": -8,
      "width": 1936,
      "height": 1056
    },
    "project-settings": {
      "x": 672,
      "y": 240,
      "width": 600,
      "height": 565
    },
    "builder": {
      "x": 702,
      "y": 140,
      "width": 670,
      "height": 739
    }
  },
  "panelLabelWidth": {
    "inspector": null,
    "builder": null
  },
  "panelLabelWidth.inspector": null,
  "panelLabelWidth.builder": null
}
